<root version="65">
	<item name="configSimple" version="7" />
	<item name="CWAssetCfg" version="14" />
	<item name="itemtab" version="17" />
	<item name="dropdata" version="17" />
	<item name="dropgroup" version="17" />
	<item name="itemcommon" version="17" />
	<item name="itemgift" version="17" />
	<item name="itemtype" version="17" />
	<item name="buildbasics" version="18" />
	<item name="buildskin" version="18" />
	<item name="buildlevel" version="18" />
	<item name="heroskill" version="19" />
	<item name="herolevel" version="19" />
	<item name="role_life" version="20" />
	<item name="heropinchface" version="21" />
	<item name="herogenerate" version="21" />
	<item name="heroattribute" version="22" />
	<item name="herotransfer" version="22" />
	<item name="weightpool" version="22" />
	<item name="meshconfig" version="23" />
	<item name="match" version="23" />
	<item name="filter" version="23" />
	<item name="option" version="23" />
	<item name="channel" version="23" />
	<item name="time" version="23" />
	<item name="npcskill" version="24" />
	<item name="npcgenerate" version="24" />
	<item name="fighter" version="24" />
	<item name="player" version="25" />
	<item name="leave" version="25" />
	<item name="enter" version="25" />
	<item name="equiptype" version="25" />
	<item name="itemequip" version="25" />
	<item name="camptext" version="25" />
	<item name="tipstext" version="25" />
	<item name="itemtext" version="25" />
	<item name="rolebasetext" version="25" />
	<item name="reset" version="26" />
	<item name="traincamp" version="28" />
	<item name="maincamp_camera" version="28" />
	<item name="clinic" version="28" />
	<item name="herochancel" version="28" />
	<item name="herochanceltab" version="28" />
	<item name="itemdrug" version="28" />
	<item name="camprecord" version="29" />
	<item name="record" version="29" />
	<item name="element" version="30" />
	<item name="maincamp_resource" version="31" />
	<item name="recruitment_resource" version="31" />
	<item name="character_resource" version="31" />
	<item name="common_resource" version="31" />
	<item name="item_resource" version="31" />
	<item name="RenderCaptureCfg" version="32" />
	<item name="route" version="32" />
	<item name="explore" version="35" />
	<item name="config" version="39" />
	<item name="recruitdivisor" version="48" />
	<item name="recruitrefresh" version="49" />
	<item name="heroment" version="50" />
	<item name="itemment" version="52" />
	<item name="heroname" version="57" />
	<item name="herocharacter" version="58" />
	<item name="herorace" version="58" />
	<item name="heroprofession" version="58" />
	<item name="herobackground" version="58" />
	<item name="prompttext" version="59" />
	<item name="uitext" version="62" />
	<item name="class" version="63" />
	<item name="eventgroup" version="64" />
	<item name="event" version="65" />
	<item name="chapter" version="65" />
</root>