<?xml version = '1.0' encoding = 'utf-8' ?>
<config>
	<file name="C-成就-成就配置-(框架定义,策划填写).xlsx" type="3" md5client="" md5server="602780d146de29ad40be5c0caccdf01b"/>
	<file name="D-道具-道具背包-(框架定义,后端填写).xlsx" type="3" md5client="" md5server="d189bf631f078aed87a7bb09c492426a"/>
	<file name="D-道具-道具类型-(框架定义,后端填写).xlsx" type="3" md5client="" md5server="0acb0c035e1036fe2592b09779695b1f"/>
	<file name="D-道具-公共配置-(后端定义,策划填写).xlsx" type="3" md5client="" md5server="093305826e486c32de1381310ec47132"/>
	<file name="D-道具-礼包配置-(后端定义,策划填写).xlsx" type="3" md5client="" md5server="5de5e878c00215ccab93ff6ce08756b0"/>
	<file name="D-掉落-掉落配置-(框架定义,策划填写).xlsx" type="3" md5client="" md5server="edb57e167f3c32e1a824aa18a585a881"/>
	<file name="G-关系-关系配置-(框架定义,策划填写).xlsx" type="3" md5client="" md5server="5d9331f4f85c88a0d2aeca78cfcf1c93"/>
	<file name="K-框架-配置列表-(框架定义,后端维护).xlsx" type="3" md5client="" md5server="74c814464fb919404838b1d756819330"/>
	<file name="K-框架-配置列表-(框架维护,请勿修改).xlsx" type="3" md5client="" md5server="b0df58dfed220013d3755a6fe8172a95"/>
	<file name="K-框架-屏蔽字符-(框架维护,请勿修改).xlsx" type="3" md5client="" md5server="4f3c8869de1f5a39b08c2b1106aabc9c"/>
	<file name="K-框架-渠道配置-(框架定义,后端维护).xlsx" type="3" md5client="" md5server="839a87a99fb21f10cf910bace7466ea6"/>
	<file name="K-框架-全局常量-(框架使用,请勿修改).xlsx" type="3" md5client="" md5server="b4e067bf397caaac41e0b2fc5b82f428"/>
	<file name="K-框架-时间配置-(框架定义,策划填写).xlsx" type="3" md5client="" md5server="4020f452c4b7b8b295209dde52efafff"/>
	<file name="K-框架-数据模板-(框架维护,请勿修改).xlsx" type="3" md5client="" md5server="d3f6e2668b7968a91cf92a5660a62b72"/>
	<file name="K-框架-随机权重-(框架定义,策划填写).xlsx" type="3" md5client="" md5server="2a5b36a48f73d805b69442bed0c46b15"/>
	<file name="K-框架-条件定义-(框架定义,后端维护).xlsx" type="3" md5client="" md5server="e49534e87e516d902e03e821e3a0b949"/>
	<file name="K-框架-条件配置-(框架定义,策划填写).xlsx" type="3" md5client="" md5server="11df9121cdf877fd717b57485d72f74a"/>
	<file name="K-框架-玩家属性-(框架维护,请勿修改).xlsx" type="3" md5client="" md5server="67ac579c049baed291685f71b4dcd9cf"/>
	<file name="K-框架-执行输出-(框架定义,策划填写).xlsx" type="3" md5client="" md5server="8d8ccf8f9f7ec6568af2de65d0b51448"/>
	<file name="P-排行-排行配置-(框架定义,策划填写).xlsx" type="3" md5client="" md5server="78f406e9702b70bf0fab219bb3c55cc3"/>
	<file name="P-匹配-名字随机-(后端定义,策划填写).xlsx" type="3" md5client="" md5server="2cb5ff19787ca0a68aa49653ffa8da3d"/>
	<file name="P-匹配-匹配设置-(后端定义,策划填写).xlsx" type="3" md5client="" md5server="10c9b4242e0febce3aa900f4ece77066"/>
	<file name="Q-签到-签到配置-(框架定义,策划填写).xlsx" type="3" md5client="" md5server="1ff2472bb132760d73ae30e3d4e6f3c8"/>
	<file name="Q-区服-区服列表-(后端定义,策划填写).xlsx" type="3" md5client="" md5server="8e8e8d50ce267f0ab40be4e484d84ad0"/>
	<file name="R-任务-任务链表-(框架定义,策划填写).xlsx" type="3" md5client="" md5server="031aabd747f18bf65e87a8cd91f5c55b"/>
	<file name="R-任务-任务配置-(框架定义,策划填写).xlsx" type="3" md5client="" md5server="c8f72cd5a553ae70ef2dcb4a4add1efa"/>
	<file name="S-商店-商店配置-(框架定义,策划填写).xlsx" type="3" md5client="" md5server="58418dad67c3710d5603e921f2c1c3d0"/>
	<file name="S-商店-商品配置-(框架定义,策划填写).xlsx" type="3" md5client="" md5server="ba75db42b68b1f84c2f9f29f60e39c4a"/>
	<file name="W-玩家-进入游戏-(框架定义,后端维护).xlsx" type="3" md5client="" md5server="e52d2af6524888af17fcbf3087eab5ee"/>
	<file name="W-玩家-属性重置-(框架定义,策划填写).xlsx" type="3" md5client="" md5server="756357ed0c34df5ad1afccfc32196b4f"/>
	<file name="W-玩家-玩家属性-(框架定义,后端维护).xlsx" type="3" md5client="" md5server="9ed5a1afd9fa7f890e489013b5534606"/>
	<file name="W-玩家-新建角色-(框架定义,策划填写).xlsx" type="3" md5client="" md5server="d204aa23a9f096aa804399240c5f18eb"/>
	<file name="Y-英雄-脚印配置-(后端定义,策划填写).xlsx" type="3" md5client="" md5server="5bd4e3563da345c7e6f86e03863c7c51"/>
	<file name="Y-英雄-特效配置-(后端定义,策划填写).xlsx" type="3" md5client="" md5server="cb08d6178189d33a0a3dfa8d478be737"/>
	<file name="Y-英雄-英雄配置-(后端定义,策划填写).xlsx" type="3" md5client="" md5server="9edfa4df1bac34b49b0e7c20f07a81e9"/>
</config>
